{
    "1211_PDAM_KABANJAHE": {
        "key": "1211_PDAM_KABANJAHE",
        "nama": "PDAM Kabanjahe",
        "kode_daerah": "1206",
        "kode_daerah_simspam": "1211",
        "kapasitas_terpasang_l_per_detik": 172,
        "kapasitas_produksi_l_per_detik": 172,
        "kapasitas_distribusi_l_per_detik": 155,
        "kapasitas_air_terjual_l_per_detik": 139.11,
        "kapasitas_belum_terpakai_l_per_detik": 0,
        "kehilangan_air_persen": 10.25,
        "sambungan_rumah_unit": 10723,
        "updated_at": "2018/10/09",
        "rimayat_sr": {
            "2010": 0,
            "2011": 0,
            "2012": 0,
            "2013": 0,
            "2014": 0,
            "2015": 0,
            "2016": 0,
            "2017": 0,
            "2018": 0
        },
        "kat_pelayanan": "KOTA",
        "kat_pengelolaan": "PDAM",
        "hidran_umum_unit": 0,
        "sambungan_komersial_non_domestik": 0,
        "penduduk_terlayani_jiwa": 39640,
        "persentase_pelayanan_persen": 11.29,
        "total_jam_oprasional_perhari": 14,
        "target_sambungan_rumah_unit": 0,
        "target_penduduk_terlayani_jiwa": 0,
        "target_cakupan_layanan_persen": 0,
        "idle_capacity_yang_dimanfaatkan_l_per_detik": 0,
        "rencana_penambahan_capacity_uprating_l_per_detaik": 0,
        "rencana_penambahan_capacity_pembangunan_unit_baru_l_per_detaik": 0,
        "rencana_kebutuhan_capacity_air_baku_l_per_detik": 0,
        "rencana_kebutuhan_capacity_intek_l_per_detik": 0,
        "kapasita_sumber_air_baku_l_per_detik": 0,
        "alokasi_kapasitas_air_baku_sesuai_sipa_l_per_detaik": 0,
        "kapasitas_intake_air_baku_l_per_detaik": 0,
        "catatan": "Tarif dasar lebih besar dari tarif rata-rata. Sehingga perlu konfirmasi."
    },
    "1211_IKK_TIGABINANGA": {
        "key": "1211_IKK_TIGABINANGA",
        "nama": "IKK Tigabinanga",
        "kode_daerah": "1206",
        "kode_daerah_simspam": "1211",
        "kapasitas_terpasang_l_per_detik": 18,
        "kapasitas_produksi_l_per_detik": 18,
        "kapasitas_distribusi_l_per_detik": 16,
        "kapasitas_air_terjual_l_per_detik": 14.94,
        "kapasitas_belum_terpakai_l_per_detik": 0,
        "kehilangan_air_persen": 6.64,
        "sambungan_rumah_unit": 1244,
        "updated_at": "2018/07/11",
        "rimayat_sr": {
            "2010": 0,
            "2011": 0,
            "2012": 0,
            "2013": 0,
            "2014": 0,
            "2015": 0,
            "2016": 0,
            "2017": 0,
            "2018": 0
        },
        "kat_pelayanan": "DESA",
        "kat_pengelolaan": "PDAM",
        "hidran_umum_unit": 0,
        "sambungan_komersial_non_domestik": 0,
        "penduduk_terlayani_jiwa": 4599,
        "persentase_pelayanan_persen": 1.31,
        "total_jam_oprasional_perhari": 14,
        "target_sambungan_rumah_unit": 0,
        "target_penduduk_terlayani_jiwa": 0,
        "target_cakupan_layanan_persen": 0,
        "idle_capacity_yang_dimanfaatkan_l_per_detik": 0,
        "rencana_penambahan_capacity_uprating_l_per_detaik": 0,
        "rencana_penambahan_capacity_pembangunan_unit_baru_l_per_detaik": 0,
        "rencana_kebutuhan_capacity_air_baku_l_per_detik": 0,
        "rencana_kebutuhan_capacity_intek_l_per_detik": 0,
        "kapasita_sumber_air_baku_l_per_detik": 0,
        "alokasi_kapasitas_air_baku_sesuai_sipa_l_per_detaik": 0,
        "kapasitas_intake_air_baku_l_per_detaik": 0,
        "catatan": "Data riwayat SR tidak tersedia. Sehingga perlu konfirmasi."
    },
    "1211_IKK_BARUS_JAHE": {
        "key": "1211_IKK_BARUS_JAHE",
        "nama": "IKK Barus Jahe",
        "kode_daerah": "1206",
        "kode_daerah_simspam": "1211",
        "kapasitas_terpasang_l_per_detik": 8,
        "kapasitas_produksi_l_per_detik": 8,
        "kapasitas_distribusi_l_per_detik": 7,
        "kapasitas_air_terjual_l_per_detik": 5.56,
        "kapasitas_belum_terpakai_l_per_detik": 0,
        "kehilangan_air_persen": 20.64,
        "sambungan_rumah_unit": 815,
        "updated_at": "2018/07/11",
        "rimayat_sr": {
            "2010": 0,
            "2011": 0,
            "2012": 0,
            "2013": 0,
            "2014": 0,
            "2015": 0,
            "2016": 0,
            "2017": 0,
            "2018": 0
        },
        "kat_pelayanan": "DESA",
        "kat_pengelolaan": "PDAM",
        "hidran_umum_unit": 0,
        "sambungan_komersial_non_domestik": 0,
        "penduduk_terlayani_jiwa": 3013,
        "persentase_pelayanan_persen": 0.86,
        "total_jam_oprasional_perhari": 14,
        "target_sambungan_rumah_unit": 0,
        "target_penduduk_terlayani_jiwa": 0,
        "target_cakupan_layanan_persen": 0,
        "idle_capacity_yang_dimanfaatkan_l_per_detik": 0,
        "rencana_penambahan_capacity_uprating_l_per_detaik": 0,
        "rencana_penambahan_capacity_pembangunan_unit_baru_l_per_detaik": 0,
        "rencana_kebutuhan_capacity_air_baku_l_per_detik": 0,
        "rencana_kebutuhan_capacity_intek_l_per_detik": 0,
        "kapasita_sumber_air_baku_l_per_detik": 0,
        "alokasi_kapasitas_air_baku_sesuai_sipa_l_per_detaik": 0,
        "kapasitas_intake_air_baku_l_per_detaik": 0,
        "catatan": null
    },
    "1211_IKK_TIGAPANAH": {
        "key": "1211_IKK_TIGAPANAH",
        "nama": "IKK Tigapanah",
        "kode_daerah": "1206",
        "kode_daerah_simspam": "1211",
        "kapasitas_terpasang_l_per_detik": 28,
        "kapasitas_produksi_l_per_detik": 28,
        "kapasitas_distribusi_l_per_detik": 25,
        "kapasitas_air_terjual_l_per_detik": 6.87,
        "kapasitas_belum_terpakai_l_per_detik": 0,
        "kehilangan_air_persen": 72.53,
        "sambungan_rumah_unit": 1069,
        "updated_at": "2018/07/11",
        "rimayat_sr": {
            "2010": 0,
            "2011": 0,
            "2012": 0,
            "2013": 0,
            "2014": 0,
            "2015": 0,
            "2016": 0,
            "2017": 0,
            "2018": 0
        },
        "kat_pelayanan": "KOTA",
        "kat_pengelolaan": "PDAM",
        "hidran_umum_unit": 0,
        "sambungan_komersial_non_domestik": 0,
        "penduduk_terlayani_jiwa": 3952,
        "persentase_pelayanan_persen": 1.13,
        "total_jam_oprasional_perhari": 14,
        "target_sambungan_rumah_unit": 0,
        "target_penduduk_terlayani_jiwa": 0,
        "target_cakupan_layanan_persen": 0,
        "idle_capacity_yang_dimanfaatkan_l_per_detik": 0,
        "rencana_penambahan_capacity_uprating_l_per_detaik": 0,
        "rencana_penambahan_capacity_pembangunan_unit_baru_l_per_detaik": 0,
        "rencana_kebutuhan_capacity_air_baku_l_per_detik": 0,
        "rencana_kebutuhan_capacity_intek_l_per_detik": 0,
        "kapasita_sumber_air_baku_l_per_detik": 0,
        "alokasi_kapasitas_air_baku_sesuai_sipa_l_per_detaik": 0,
        "kapasitas_intake_air_baku_l_per_detaik": 0,
        "catatan": null
    },
    "1211_IKK_LAU_BAWANG": {
        "key": "1211_IKK_LAU_BAWANG",
        "nama": "IKK Lau Bawang",
        "kode_daerah": "1206",
        "kode_daerah_simspam": "1211",
        "kapasitas_terpasang_l_per_detik": 4,
        "kapasitas_produksi_l_per_detik": 4,
        "kapasitas_distribusi_l_per_detik": 4,
        "kapasitas_air_terjual_l_per_detik": 1.44,
        "kapasitas_belum_terpakai_l_per_detik": 0,
        "kehilangan_air_persen": 63.95,
        "sambungan_rumah_unit": 159,
        "updated_at": "2018/07/11",
        "rimayat_sr": {
            "2010": 0,
            "2011": 0,
            "2012": 0,
            "2013": 0,
            "2014": 0,
            "2015": 0,
            "2016": 0,
            "2017": 0,
            "2018": 0
        },
        "kat_pelayanan": "DESA",
        "kat_pengelolaan": "PDAM",
        "hidran_umum_unit": 0,
        "sambungan_komersial_non_domestik": 0,
        "penduduk_terlayani_jiwa": 588,
        "persentase_pelayanan_persen": 0.17,
        "total_jam_oprasional_perhari": 14,
        "target_sambungan_rumah_unit": 0,
        "target_penduduk_terlayani_jiwa": 0,
        "target_cakupan_layanan_persen": 0,
        "idle_capacity_yang_dimanfaatkan_l_per_detik": 0,
        "rencana_penambahan_capacity_uprating_l_per_detaik": 0,
        "rencana_penambahan_capacity_pembangunan_unit_baru_l_per_detaik": 0,
        "rencana_kebutuhan_capacity_air_baku_l_per_detik": 0,
        "rencana_kebutuhan_capacity_intek_l_per_detik": 0,
        "kapasita_sumber_air_baku_l_per_detik": 0,
        "alokasi_kapasitas_air_baku_sesuai_sipa_l_per_detaik": 0,
        "kapasitas_intake_air_baku_l_per_detaik": 0,
        "catatan": null
    },
    "1211_IKK_SIMPANG_EMPAT": {
        "key": "1211_IKK_SIMPANG_EMPAT",
        "nama": "IKK Simpang Empat",
        "kode_daerah": "1206",
        "kode_daerah_simspam": "1211",
        "kapasitas_terpasang_l_per_detik": 4,
        "kapasitas_produksi_l_per_detik": 4,
        "kapasitas_distribusi_l_per_detik": 4,
        "kapasitas_air_terjual_l_per_detik": 0.63,
        "kapasitas_belum_terpakai_l_per_detik": 0,
        "kehilangan_air_persen": 84.28,
        "sambungan_rumah_unit": 252,
        "updated_at": "2018/07/11",
        "rimayat_sr": {
            "2010": 0,
            "2011": 0,
            "2012": 0,
            "2013": 0,
            "2014": 0,
            "2015": 0,
            "2016": 0,
            "2017": 0,
            "2018": 0
        },
        "kat_pelayanan": "DESA",
        "kat_pengelolaan": "PDAM",
        "hidran_umum_unit": 0,
        "sambungan_komersial_non_domestik": 0,
        "penduduk_terlayani_jiwa": 932,
        "persentase_pelayanan_persen": 0.27,
        "total_jam_oprasional_perhari": 14,
        "target_sambungan_rumah_unit": 0,
        "target_penduduk_terlayani_jiwa": 0,
        "target_cakupan_layanan_persen": 0,
        "idle_capacity_yang_dimanfaatkan_l_per_detik": 0,
        "rencana_penambahan_capacity_uprating_l_per_detaik": 0,
        "rencana_penambahan_capacity_pembangunan_unit_baru_l_per_detaik": 0,
        "rencana_kebutuhan_capacity_air_baku_l_per_detik": 0,
        "rencana_kebutuhan_capacity_intek_l_per_detik": 0,
        "kapasita_sumber_air_baku_l_per_detik": 0,
        "alokasi_kapasitas_air_baku_sesuai_sipa_l_per_detaik": 0,
        "kapasitas_intake_air_baku_l_per_detaik": 0,
        "catatan": null
    },
    "1211_IKK_KUTA_BULUH": {
        "key": "1211_IKK_KUTA_BULUH",
        "nama": "IKK Kuta Buluh",
        "kode_daerah": "1206",
        "kode_daerah_simspam": "1211",
        "kapasitas_terpasang_l_per_detik": 9,
        "kapasitas_produksi_l_per_detik": 9,
        "kapasitas_distribusi_l_per_detik": 8,
        "kapasitas_air_terjual_l_per_detik": 1.36,
        "kapasitas_belum_terpakai_l_per_detik": 0,
        "kehilangan_air_persen": 83.06,
        "sambungan_rumah_unit": 314,
        "updated_at": "2018/07/11",
        "rimayat_sr": {
            "2010": 0,
            "2011": 0,
            "2012": 0,
            "2013": 0,
            "2014": 0,
            "2015": 0,
            "2016": 0,
            "2017": 0,
            "2018": 0
        },
        "kat_pelayanan": "DESA",
        "kat_pengelolaan": "PDAM",
        "hidran_umum_unit": 0,
        "sambungan_komersial_non_domestik": 0,
        "penduduk_terlayani_jiwa": 1161,
        "persentase_pelayanan_persen": 0.33,
        "total_jam_oprasional_perhari": 14,
        "target_sambungan_rumah_unit": 0,
        "target_penduduk_terlayani_jiwa": 0,
        "target_cakupan_layanan_persen": 0,
        "idle_capacity_yang_dimanfaatkan_l_per_detik": 0,
        "rencana_penambahan_capacity_uprating_l_per_detaik": 0,
        "rencana_penambahan_capacity_pembangunan_unit_baru_l_per_detaik": 0,
        "rencana_kebutuhan_capacity_air_baku_l_per_detik": 0,
        "rencana_kebutuhan_capacity_intek_l_per_detik": 0,
        "kapasita_sumber_air_baku_l_per_detik": 0,
        "alokasi_kapasitas_air_baku_sesuai_sipa_l_per_detaik": 0,
        "kapasitas_intake_air_baku_l_per_detaik": 0,
        "catatan": null
    },
    "1211_IKK_JUHAR": {
        "key": "1211_IKK_JUHAR",
        "nama": "IKK Juhar",
        "kode_daerah": "1206",
        "kode_daerah_simspam": "1211",
        "kapasitas_terpasang_l_per_detik": 9,
        "kapasitas_produksi_l_per_detik": 9,
        "kapasitas_distribusi_l_per_detik": 8,
        "kapasitas_air_terjual_l_per_detik": 3.11,
        "kapasitas_belum_terpakai_l_per_detik": 0,
        "kehilangan_air_persen": 61.11,
        "sambungan_rumah_unit": 664,
        "updated_at": "2018/07/11",
        "rimayat_sr": {
            "2010": 0,
            "2011": 0,
            "2012": 0,
            "2013": 0,
            "2014": 0,
            "2015": 0,
            "2016": 0,
            "2017": 0,
            "2018": 0
        },
        "kat_pelayanan": "DESA",
        "kat_pengelolaan": "PDAM",
        "hidran_umum_unit": 0,
        "sambungan_komersial_non_domestik": 0,
        "penduduk_terlayani_jiwa": 2455,
        "persentase_pelayanan_persen": 0.7,
        "total_jam_oprasional_perhari": 14,
        "target_sambungan_rumah_unit": 0,
        "target_penduduk_terlayani_jiwa": 0,
        "target_cakupan_layanan_persen": 0,
        "idle_capacity_yang_dimanfaatkan_l_per_detik": 0,
        "rencana_penambahan_capacity_uprating_l_per_detaik": 0,
        "rencana_penambahan_capacity_pembangunan_unit_baru_l_per_detaik": 0,
        "rencana_kebutuhan_capacity_air_baku_l_per_detik": 0,
        "rencana_kebutuhan_capacity_intek_l_per_detik": 0,
        "kapasita_sumber_air_baku_l_per_detik": 0,
        "alokasi_kapasitas_air_baku_sesuai_sipa_l_per_detaik": 0,
        "kapasitas_intake_air_baku_l_per_detaik": 0,
        "catatan": null
    },
    "1211_IKK_MUNTHE": {
        "key": "1211_IKK_MUNTHE",
        "nama": "IKK Munthe",
        "kode_daerah": "1206",
        "kode_daerah_simspam": "1211",
        "kapasitas_terpasang_l_per_detik": 4,
        "kapasitas_produksi_l_per_detik": 4,
        "kapasitas_distribusi_l_per_detik": 4,
        "kapasitas_air_terjual_l_per_detik": 1.34,
        "kapasitas_belum_terpakai_l_per_detik": 0,
        "kehilangan_air_persen": 66.39,
        "sambungan_rumah_unit": 335,
        "updated_at": "2018/07/11",
        "rimayat_sr": {
            "2010": 0,
            "2011": 0,
            "2012": 0,
            "2013": 0,
            "2014": 0,
            "2015": 0,
            "2016": 0,
            "2017": 0,
            "2018": 0
        },
        "kat_pelayanan": "DESA",
        "kat_pengelolaan": "PDAM",
        "hidran_umum_unit": 0,
        "sambungan_komersial_non_domestik": 0,
        "penduduk_terlayani_jiwa": 1238,
        "persentase_pelayanan_persen": 0.35,
        "total_jam_oprasional_perhari": 14,
        "target_sambungan_rumah_unit": 0,
        "target_penduduk_terlayani_jiwa": 0,
        "target_cakupan_layanan_persen": 0,
        "idle_capacity_yang_dimanfaatkan_l_per_detik": 0,
        "rencana_penambahan_capacity_uprating_l_per_detaik": 0,
        "rencana_penambahan_capacity_pembangunan_unit_baru_l_per_detaik": 0,
        "rencana_kebutuhan_capacity_air_baku_l_per_detik": 0,
        "rencana_kebutuhan_capacity_intek_l_per_detik": 0,
        "kapasita_sumber_air_baku_l_per_detik": 0,
        "alokasi_kapasitas_air_baku_sesuai_sipa_l_per_detaik": 0,
        "kapasitas_intake_air_baku_l_per_detaik": 0,
        "catatan": null
    },
    "1211_IKK_PAYUNG": {
        "key": "1211_IKK_PAYUNG",
        "nama": "IKK Payung",
        "kode_daerah": "1206",
        "kode_daerah_simspam": "1211",
        "kapasitas_terpasang_l_per_detik": 10,
        "kapasitas_produksi_l_per_detik": 10,
        "kapasitas_distribusi_l_per_detik": 9,
        "kapasitas_air_terjual_l_per_detik": 3.9,
        "kapasitas_belum_terpakai_l_per_detik": 0,
        "kehilangan_air_persen": 56.72,
        "sambungan_rumah_unit": 564,
        "updated_at": "2018/07/11",
        "rimayat_sr": {
            "2010": 0,
            "2011": 0,
            "2012": 0,
            "2013": 0,
            "2014": 0,
            "2015": 0,
            "2016": 0,
            "2017": 0,
            "2018": 0
        },
        "kat_pelayanan": "KOTA",
        "kat_pengelolaan": "PDAM",
        "hidran_umum_unit": 0,
        "sambungan_komersial_non_domestik": 0,
        "penduduk_terlayani_jiwa": 2085,
        "persentase_pelayanan_persen": 0.59,
        "total_jam_oprasional_perhari": 14,
        "target_sambungan_rumah_unit": 0,
        "target_penduduk_terlayani_jiwa": 0,
        "target_cakupan_layanan_persen": 0,
        "idle_capacity_yang_dimanfaatkan_l_per_detik": 0,
        "rencana_penambahan_capacity_uprating_l_per_detaik": 0,
        "rencana_penambahan_capacity_pembangunan_unit_baru_l_per_detaik": 0,
        "rencana_kebutuhan_capacity_air_baku_l_per_detik": 0,
        "rencana_kebutuhan_capacity_intek_l_per_detik": 0,
        "kapasita_sumber_air_baku_l_per_detik": 0,
        "alokasi_kapasitas_air_baku_sesuai_sipa_l_per_detaik": 0,
        "kapasitas_intake_air_baku_l_per_detaik": 0,
        "catatan": null
    },
    "1211_IKK_PERBESI": {
        "key": "1211_IKK_PERBESI",
        "nama": "IKK Perbesi",
        "kode_daerah": "1206",
        "kode_daerah_simspam": "1211",
        "kapasitas_terpasang_l_per_detik": 6,
        "kapasitas_produksi_l_per_detik": 6,
        "kapasitas_distribusi_l_per_detik": 5,
        "kapasitas_air_terjual_l_per_detik": 1.48,
        "kapasitas_belum_terpakai_l_per_detik": 0,
        "kehilangan_air_persen": 70.31,
        "sambungan_rumah_unit": 407,
        "updated_at": "2018/07/11",
        "rimayat_sr": {
            "2010": 0,
            "2011": 0,
            "2012": 0,
            "2013": 0,
            "2014": 0,
            "2015": 0,
            "2016": 0,
            "2017": 0,
            "2018": 0
        },
        "kat_pelayanan": "KOTA",
        "kat_pengelolaan": "PDAM",
        "hidran_umum_unit": 0,
        "sambungan_komersial_non_domestik": 0,
        "penduduk_terlayani_jiwa": 1505,
        "persentase_pelayanan_persen": 0.43,
        "total_jam_oprasional_perhari": 14,
        "target_sambungan_rumah_unit": 0,
        "target_penduduk_terlayani_jiwa": 0,
        "target_cakupan_layanan_persen": 0,
        "idle_capacity_yang_dimanfaatkan_l_per_detik": 0,
        "rencana_penambahan_capacity_uprating_l_per_detaik": 0,
        "rencana_penambahan_capacity_pembangunan_unit_baru_l_per_detaik": 0,
        "rencana_kebutuhan_capacity_air_baku_l_per_detik": 0,
        "rencana_kebutuhan_capacity_intek_l_per_detik": 0,
        "kapasita_sumber_air_baku_l_per_detik": 0,
        "alokasi_kapasitas_air_baku_sesuai_sipa_l_per_detaik": 0,
        "kapasitas_intake_air_baku_l_per_detaik": 0,
        "catatan": null
    },
    "1211_IKK_MARDINDING": {
        "key": "1211_IKK_MARDINDING",
        "nama": "IKK Mardinding",
        "kode_daerah": "1206",
        "kode_daerah_simspam": "1211",
        "kapasitas_terpasang_l_per_detik": 0,
        "kapasitas_produksi_l_per_detik": 0,
        "kapasitas_distribusi_l_per_detik": 0,
        "kapasitas_air_terjual_l_per_detik": 0,
        "kapasitas_belum_terpakai_l_per_detik": 0,
        "kehilangan_air_persen": 0,
        "sambungan_rumah_unit": 0,
        "updated_at": "2018/07/11",
        "rimayat_sr": {
            "2010": 0,
            "2011": 0,
            "2012": 0,
            "2013": 0,
            "2014": 0,
            "2015": 0,
            "2016": 0,
            "2017": 0,
            "2018": 0
        },
        "kat_pelayanan": null,
        "kat_pengelolaan": null,
        "hidran_umum_unit": null,
        "sambungan_komersial_non_domestik": null,
        "penduduk_terlayani_jiwa": null,
        "persentase_pelayanan_persen": 0,
        "total_jam_oprasional_perhari": 0,
        "target_sambungan_rumah_unit": 0,
        "target_penduduk_terlayani_jiwa": 0,
        "target_cakupan_layanan_persen": 0,
        "idle_capacity_yang_dimanfaatkan_l_per_detik": 0,
        "rencana_penambahan_capacity_uprating_l_per_detaik": 0,
        "rencana_penambahan_capacity_pembangunan_unit_baru_l_per_detaik": 0,
        "rencana_kebutuhan_capacity_air_baku_l_per_detik": 0,
        "rencana_kebutuhan_capacity_intek_l_per_detik": 0,
        "kapasita_sumber_air_baku_l_per_detik": 0,
        "alokasi_kapasitas_air_baku_sesuai_sipa_l_per_detaik": 0,
        "kapasitas_intake_air_baku_l_per_detaik": 0,
        "catatan": null
    }
}