{
    "3277_SPAM_CIMAHI_UTARA": {
        "key": "3277_SPAM_CIMAHI_UTARA",
        "nama": "SPAM CIMAHI UTARA",
        "kode_daerah": "3277",
        "kode_daerah_simspam": "3277",
        "kapasitas_terpasang_l_per_detik": 50,
        "kapasitas_produksi_l_per_detik": 50,
        "kapasitas_distribusi_l_per_detik": 48,
        "kapasitas_air_terjual_l_per_detik": 40.85,
        "kapasitas_belum_terpakai_l_per_detik": 0,
        "kehilangan_air_persen": 14,
        "sambungan_rumah_unit": 4252,
        "updated_at": "2019/09/18",
        "rimayat_sr": {
            "2010": 0,
            "2011": 0,
            "2012": 0,
            "2013": 0,
            "2014": 0,
            "2015": 50,
            "2016": 274,
            "2017": 880,
            "2018": 2008
        },
        "kat_pelayanan": "KOTA",
        "kat_pengelolaan": "UPT",
        "hidran_umum_unit": 0,
        "sambungan_komersial_non_domestik": 2,
        "penduduk_terlayani_jiwa": 21260,
        "persentase_pelayanan_persen": 3.93,
        "total_jam_oprasional_perhari": 24,
        "target_sambungan_rumah_unit": 4252,
        "target_penduduk_terlayani_jiwa": 21260,
        "target_cakupan_layanan_persen": 4,
        "idle_capacity_yang_dimanfaatkan_l_per_detik": 819,
        "rencana_penambahan_capacity_uprating_l_per_detaik": 0,
        "rencana_penambahan_capacity_pembangunan_unit_baru_l_per_detaik": 0,
        "rencana_kebutuhan_capacity_air_baku_l_per_detik": 120,
        "rencana_kebutuhan_capacity_intek_l_per_detik": 0,
        "kapasita_sumber_air_baku_l_per_detik": 300,
        "alokasi_kapasitas_air_baku_sesuai_sipa_l_per_detaik": 120,
        "kapasitas_intake_air_baku_l_per_detaik": 50,
        "catatan": "Dari Satker : IKK dibangun pada tahun T.A. 2015"
    },
    "3277_SPAM_LEUWILAYUNG": {
        "key": "3277_SPAM_LEUWILAYUNG",
        "nama": "SPAM Leuwilayung",
        "kode_daerah": "3277",
        "kode_daerah_simspam": "3277",
        "kapasitas_terpasang_l_per_detik": 0,
        "kapasitas_produksi_l_per_detik": 0,
        "kapasitas_distribusi_l_per_detik": 0,
        "kapasitas_air_terjual_l_per_detik": 0,
        "kapasitas_belum_terpakai_l_per_detik": 0,
        "kehilangan_air_persen": 0,
        "sambungan_rumah_unit": 0,
        "updated_at": "2019/09/17",
        "rimayat_sr": {
            "2010": 0,
            "2011": 0,
            "2012": 0,
            "2013": 0,
            "2014": 0,
            "2015": 0,
            "2016": 0,
            "2017": 0,
            "2018": 0
        },
        "kat_pelayanan": null,
        "kat_pengelolaan": null,
        "hidran_umum_unit": null,
        "sambungan_komersial_non_domestik": null,
        "penduduk_terlayani_jiwa": null,
        "persentase_pelayanan_persen": 0,
        "total_jam_oprasional_perhari": 0,
        "target_sambungan_rumah_unit": 0,
        "target_penduduk_terlayani_jiwa": 0,
        "target_cakupan_layanan_persen": 0,
        "idle_capacity_yang_dimanfaatkan_l_per_detik": 0,
        "rencana_penambahan_capacity_uprating_l_per_detaik": 0,
        "rencana_penambahan_capacity_pembangunan_unit_baru_l_per_detaik": 0,
        "rencana_kebutuhan_capacity_air_baku_l_per_detik": 0,
        "rencana_kebutuhan_capacity_intek_l_per_detik": 0,
        "kapasita_sumber_air_baku_l_per_detik": 0,
        "alokasi_kapasitas_air_baku_sesuai_sipa_l_per_detaik": 0,
        "kapasitas_intake_air_baku_l_per_detaik": 0,
        "catatan": null
    },
    "3277_SPAM_GAMBUNG": {
        "key": "3277_SPAM_GAMBUNG",
        "nama": "SPAM Gambung",
        "kode_daerah": "3277",
        "kode_daerah_simspam": "3277",
        "kapasitas_terpasang_l_per_detik": 0,
        "kapasitas_produksi_l_per_detik": 0,
        "kapasitas_distribusi_l_per_detik": 0,
        "kapasitas_air_terjual_l_per_detik": 0,
        "kapasitas_belum_terpakai_l_per_detik": 0,
        "kehilangan_air_persen": 0,
        "sambungan_rumah_unit": 0,
        "updated_at": "2019/09/17",
        "rimayat_sr": {
            "2010": 0,
            "2011": 0,
            "2012": 0,
            "2013": 0,
            "2014": 0,
            "2015": 0,
            "2016": 0,
            "2017": 0,
            "2018": 0
        },
        "kat_pelayanan": null,
        "kat_pengelolaan": null,
        "hidran_umum_unit": null,
        "sambungan_komersial_non_domestik": null,
        "penduduk_terlayani_jiwa": null,
        "persentase_pelayanan_persen": 0,
        "total_jam_oprasional_perhari": 0,
        "target_sambungan_rumah_unit": 0,
        "target_penduduk_terlayani_jiwa": 0,
        "target_cakupan_layanan_persen": 0,
        "idle_capacity_yang_dimanfaatkan_l_per_detik": 0,
        "rencana_penambahan_capacity_uprating_l_per_detaik": 0,
        "rencana_penambahan_capacity_pembangunan_unit_baru_l_per_detaik": 0,
        "rencana_kebutuhan_capacity_air_baku_l_per_detik": 0,
        "rencana_kebutuhan_capacity_intek_l_per_detik": 0,
        "kapasita_sumber_air_baku_l_per_detik": 0,
        "alokasi_kapasitas_air_baku_sesuai_sipa_l_per_detaik": 0,
        "kapasitas_intake_air_baku_l_per_detaik": 0,
        "catatan": null
    }
}