{
    "3302_PURWOKERTO_BARAT_DAN_KARANGLEWAS": {
        "key": "3302_PURWOKERTO_BARAT_DAN_KARANGLEWAS",
        "nama": "PURWOKERTO BARAT DAN KARANGLEWAS",
        "kode_daerah": "3302",
        "kode_daerah_simspam": "3302",
        "kapasitas_terpasang_l_per_detik": 84,
        "kapasitas_produksi_l_per_detik": 82,
        "kapasitas_distribusi_l_per_detik": 60,
        "kapasitas_air_terjual_l_per_detik": 43.48,
        "kapasitas_belum_terpakai_l_per_detik": 2,
        "kehilangan_air_persen": 27.64,
        "sambungan_rumah_unit": 6847,
        "updated_at": "2019/10/22",
        "rimayat_sr": {
            "2010": 4321,
            "2011": 4421,
            "2012": 4523,
            "2013": 4919,
            "2014": 5056,
            "2015": 5439,
            "2016": 5817,
            "2017": 6512,
            "2018": 7186
        },
        "kat_pelayanan": "KOTA",
        "kat_pengelolaan": "PDAM",
        "hidran_umum_unit": 1,
        "sambungan_komersial_non_domestik": 338,
        "penduduk_terlayani_jiwa": 27576,
        "persentase_pelayanan_persen": 1.77,
        "total_jam_oprasional_perhari": 23,
        "target_sambungan_rumah_unit": 500,
        "target_penduduk_terlayani_jiwa": 29583,
        "target_cakupan_layanan_persen": 25,
        "idle_capacity_yang_dimanfaatkan_l_per_detik": 0,
        "rencana_penambahan_capacity_uprating_l_per_detaik": 0,
        "rencana_penambahan_capacity_pembangunan_unit_baru_l_per_detaik": 0,
        "rencana_kebutuhan_capacity_air_baku_l_per_detik": 0,
        "rencana_kebutuhan_capacity_intek_l_per_detik": 0,
        "kapasita_sumber_air_baku_l_per_detik": 121,
        "alokasi_kapasitas_air_baku_sesuai_sipa_l_per_detaik": 0,
        "kapasitas_intake_air_baku_l_per_detaik": 125,
        "catatan": "Tahun Pembangunan 1995, 2007, 2014\nSumber Dana Pembangunan juga berasal dari dana APBD dan PDAM; \nKapasitas air distribusi lebih besar dari kapasitas produksi perlu dilakukan pengecekan ulang input data/ commisioning dilapangan."
    },
    "3302_BANYUMAS_DAN_SOMAGEDE": {
        "key": "3302_BANYUMAS_DAN_SOMAGEDE",
        "nama": "BANYUMAS DAN SOMAGEDE",
        "kode_daerah": "3302",
        "kode_daerah_simspam": "3302",
        "kapasitas_terpasang_l_per_detik": 29,
        "kapasitas_produksi_l_per_detik": 28,
        "kapasitas_distribusi_l_per_detik": 42,
        "kapasitas_air_terjual_l_per_detik": 35.4,
        "kapasitas_belum_terpakai_l_per_detik": 1,
        "kehilangan_air_persen": 14.78,
        "sambungan_rumah_unit": 4396,
        "updated_at": "2019/10/22",
        "rimayat_sr": {
            "2010": 1269,
            "2011": 1322,
            "2012": 1441,
            "2013": 1582,
            "2014": 1916,
            "2015": 2134,
            "2016": 0,
            "2017": 0,
            "2018": 0
        },
        "kat_pelayanan": "KOTA",
        "kat_pengelolaan": "PDAM",
        "hidran_umum_unit": 3,
        "sambungan_komersial_non_domestik": 163,
        "penduduk_terlayani_jiwa": 16627,
        "persentase_pelayanan_persen": 1.07,
        "total_jam_oprasional_perhari": 22,
        "target_sambungan_rumah_unit": 500,
        "target_penduduk_terlayani_jiwa": 18484,
        "target_cakupan_layanan_persen": 14,
        "idle_capacity_yang_dimanfaatkan_l_per_detik": 0,
        "rencana_penambahan_capacity_uprating_l_per_detaik": 0,
        "rencana_penambahan_capacity_pembangunan_unit_baru_l_per_detaik": 0,
        "rencana_kebutuhan_capacity_air_baku_l_per_detik": 30,
        "rencana_kebutuhan_capacity_intek_l_per_detik": 0,
        "kapasita_sumber_air_baku_l_per_detik": 32,
        "alokasi_kapasitas_air_baku_sesuai_sipa_l_per_detaik": 30,
        "kapasitas_intake_air_baku_l_per_detaik": 32,
        "catatan": "Sumber Dana Pembangunan juga berasal dari APBD, PDAM dan Pinjaman Luar Negeri\t;"
    },
    "3302_SOKARAJA_DAN_KALIBAGOR": {
        "key": "3302_SOKARAJA_DAN_KALIBAGOR",
        "nama": "SOKARAJA DAN KALIBAGOR",
        "kode_daerah": "3302",
        "kode_daerah_simspam": "3302",
        "kapasitas_terpasang_l_per_detik": 48,
        "kapasitas_produksi_l_per_detik": 46,
        "kapasitas_distribusi_l_per_detik": 41,
        "kapasitas_air_terjual_l_per_detik": 38.95,
        "kapasitas_belum_terpakai_l_per_detik": 2,
        "kehilangan_air_persen": 5.35,
        "sambungan_rumah_unit": 6169,
        "updated_at": "2019/10/22",
        "rimayat_sr": {
            "2010": 0,
            "2011": 0,
            "2012": 0,
            "2013": 1750,
            "2014": 1791,
            "2015": 5099,
            "2016": 5750,
            "2017": 5901,
            "2018": 6493
        },
        "kat_pelayanan": "KOTA",
        "kat_pengelolaan": "PDAM",
        "hidran_umum_unit": 0,
        "sambungan_komersial_non_domestik": 324,
        "penduduk_terlayani_jiwa": 24383,
        "persentase_pelayanan_persen": 1.57,
        "total_jam_oprasional_perhari": 22,
        "target_sambungan_rumah_unit": 500,
        "target_penduduk_terlayani_jiwa": 26360,
        "target_cakupan_layanan_persen": 30,
        "idle_capacity_yang_dimanfaatkan_l_per_detik": 0,
        "rencana_penambahan_capacity_uprating_l_per_detaik": 0,
        "rencana_penambahan_capacity_pembangunan_unit_baru_l_per_detaik": 0,
        "rencana_kebutuhan_capacity_air_baku_l_per_detik": 0,
        "rencana_kebutuhan_capacity_intek_l_per_detik": 0,
        "kapasita_sumber_air_baku_l_per_detik": 49,
        "alokasi_kapasitas_air_baku_sesuai_sipa_l_per_detaik": 0,
        "kapasitas_intake_air_baku_l_per_detaik": 52,
        "catatan": "Sumber Dana Pembangunan juga berasal dari dana APBD, PDAM dan pinjaman luar negeri\t; Data kapasitas unit kosong."
    },
    "3302_KEMBARAN_DAN_SUMBANG": {
        "key": "3302_KEMBARAN_DAN_SUMBANG",
        "nama": "KEMBARAN DAN SUMBANG",
        "kode_daerah": "3302",
        "kode_daerah_simspam": "3302",
        "kapasitas_terpasang_l_per_detik": 10,
        "kapasitas_produksi_l_per_detik": 9,
        "kapasitas_distribusi_l_per_detik": 9,
        "kapasitas_air_terjual_l_per_detik": 8,
        "kapasitas_belum_terpakai_l_per_detik": 1,
        "kehilangan_air_persen": 11.11,
        "sambungan_rumah_unit": 832,
        "updated_at": "2019/10/22",
        "rimayat_sr": {
            "2010": 0,
            "2011": 0,
            "2012": 0,
            "2013": 0,
            "2014": 0,
            "2015": 0,
            "2016": 0,
            "2017": 0,
            "2018": 0
        },
        "kat_pelayanan": "KOTA",
        "kat_pengelolaan": "PDAM",
        "hidran_umum_unit": 28,
        "sambungan_komersial_non_domestik": 32,
        "penduduk_terlayani_jiwa": 0,
        "persentase_pelayanan_persen": 0,
        "total_jam_oprasional_perhari": 24,
        "target_sambungan_rumah_unit": 0,
        "target_penduduk_terlayani_jiwa": 0,
        "target_cakupan_layanan_persen": 0,
        "idle_capacity_yang_dimanfaatkan_l_per_detik": 0,
        "rencana_penambahan_capacity_uprating_l_per_detaik": 0,
        "rencana_penambahan_capacity_pembangunan_unit_baru_l_per_detaik": 0,
        "rencana_kebutuhan_capacity_air_baku_l_per_detik": 0,
        "rencana_kebutuhan_capacity_intek_l_per_detik": 0,
        "kapasita_sumber_air_baku_l_per_detik": 0,
        "alokasi_kapasitas_air_baku_sesuai_sipa_l_per_detaik": 0,
        "kapasitas_intake_air_baku_l_per_detaik": 0,
        "catatan": "Sumber dana pembangunan juga berasal dari dana APBD, PDAM, dan pinjaman luar negeri"
    },
    "3302_KOTA_PURWOKERTO": {
        "key": "3302_KOTA_PURWOKERTO",
        "nama": "KOTA PURWOKERTO",
        "kode_daerah": "3302",
        "kode_daerah_simspam": "3302",
        "kapasitas_terpasang_l_per_detik": 383,
        "kapasitas_produksi_l_per_detik": 374,
        "kapasitas_distribusi_l_per_detik": 311,
        "kapasitas_air_terjual_l_per_detik": 177.47,
        "kapasitas_belum_terpakai_l_per_detik": 9,
        "kehilangan_air_persen": 43.02,
        "sambungan_rumah_unit": 20693,
        "updated_at": "2019/10/22",
        "rimayat_sr": {
            "2010": 21044,
            "2011": 21817,
            "2012": 22571,
            "2013": 25959,
            "2014": 20236,
            "2015": 19995,
            "2016": 21077,
            "2017": 22811,
            "2018": 24098
        },
        "kat_pelayanan": "KOTA",
        "kat_pengelolaan": "PDAM",
        "hidran_umum_unit": 22,
        "sambungan_komersial_non_domestik": 3383,
        "penduduk_terlayani_jiwa": 73770,
        "persentase_pelayanan_persen": 4.75,
        "total_jam_oprasional_perhari": 22,
        "target_sambungan_rumah_unit": 1000,
        "target_penduduk_terlayani_jiwa": 77228,
        "target_cakupan_layanan_persen": 42,
        "idle_capacity_yang_dimanfaatkan_l_per_detik": 0,
        "rencana_penambahan_capacity_uprating_l_per_detaik": 0,
        "rencana_penambahan_capacity_pembangunan_unit_baru_l_per_detaik": 0,
        "rencana_kebutuhan_capacity_air_baku_l_per_detik": 0,
        "rencana_kebutuhan_capacity_intek_l_per_detik": 0,
        "kapasita_sumber_air_baku_l_per_detik": 528,
        "alokasi_kapasitas_air_baku_sesuai_sipa_l_per_detaik": 0,
        "kapasitas_intake_air_baku_l_per_detaik": 544,
        "catatan": "Sumber Dana Pembangunan lainnya berasal dari APBD, PDAM, Pinjaman dan Hibah Luar Negeri;\nMohon diteliti kembali data SR."
    },
    "3302_BATURADEN": {
        "key": "3302_BATURADEN",
        "nama": "BATURADEN",
        "kode_daerah": "3302",
        "kode_daerah_simspam": "3302",
        "kapasitas_terpasang_l_per_detik": 22,
        "kapasitas_produksi_l_per_detik": 22,
        "kapasitas_distribusi_l_per_detik": 18,
        "kapasitas_air_terjual_l_per_detik": 8.85,
        "kapasitas_belum_terpakai_l_per_detik": 1,
        "kehilangan_air_persen": 50.7,
        "sambungan_rumah_unit": 1464,
        "updated_at": "2019/10/22",
        "rimayat_sr": {
            "2010": 625,
            "2011": 655,
            "2012": 674,
            "2013": 841,
            "2014": 906,
            "2015": 1007,
            "2016": 1220,
            "2017": 1457,
            "2018": 1627
        },
        "kat_pelayanan": "KOTA",
        "kat_pengelolaan": "PDAM",
        "hidran_umum_unit": 1,
        "sambungan_komersial_non_domestik": 162,
        "penduduk_terlayani_jiwa": 5993,
        "persentase_pelayanan_persen": 0.39,
        "total_jam_oprasional_perhari": 24,
        "target_sambungan_rumah_unit": 500,
        "target_penduduk_terlayani_jiwa": 8006,
        "target_cakupan_layanan_persen": 15,
        "idle_capacity_yang_dimanfaatkan_l_per_detik": 0,
        "rencana_penambahan_capacity_uprating_l_per_detaik": 0,
        "rencana_penambahan_capacity_pembangunan_unit_baru_l_per_detaik": 0,
        "rencana_kebutuhan_capacity_air_baku_l_per_detik": 0,
        "rencana_kebutuhan_capacity_intek_l_per_detik": 0,
        "kapasita_sumber_air_baku_l_per_detik": 24,
        "alokasi_kapasitas_air_baku_sesuai_sipa_l_per_detaik": 0,
        "kapasitas_intake_air_baku_l_per_detaik": 22,
        "catatan": "Sumber Dana Pembangunan juga berasal dari dana APBD dan PDAM"
    },
    "3302_PATIKRAJA": {
        "key": "3302_PATIKRAJA",
        "nama": "PATIKRAJA",
        "kode_daerah": "3302",
        "kode_daerah_simspam": "3302",
        "kapasitas_terpasang_l_per_detik": 34,
        "kapasitas_produksi_l_per_detik": 24,
        "kapasitas_distribusi_l_per_detik": 7,
        "kapasitas_air_terjual_l_per_detik": 7,
        "kapasitas_belum_terpakai_l_per_detik": 10,
        "kehilangan_air_persen": 0,
        "sambungan_rumah_unit": 1019,
        "updated_at": "2019/10/22",
        "rimayat_sr": {
            "2010": 449,
            "2011": 515,
            "2012": 591,
            "2013": 841,
            "2014": 945,
            "2015": 1042,
            "2016": 0,
            "2017": 0,
            "2018": 0
        },
        "kat_pelayanan": "KOTA",
        "kat_pengelolaan": "PDAM",
        "hidran_umum_unit": 23,
        "sambungan_komersial_non_domestik": 19,
        "penduduk_terlayani_jiwa": 6091,
        "persentase_pelayanan_persen": 0.39,
        "total_jam_oprasional_perhari": 20,
        "target_sambungan_rumah_unit": 2139,
        "target_penduduk_terlayani_jiwa": 10258,
        "target_cakupan_layanan_persen": 18,
        "idle_capacity_yang_dimanfaatkan_l_per_detik": 0,
        "rencana_penambahan_capacity_uprating_l_per_detaik": 0,
        "rencana_penambahan_capacity_pembangunan_unit_baru_l_per_detaik": 0,
        "rencana_kebutuhan_capacity_air_baku_l_per_detik": 0,
        "rencana_kebutuhan_capacity_intek_l_per_detik": 0,
        "kapasita_sumber_air_baku_l_per_detik": 0,
        "alokasi_kapasitas_air_baku_sesuai_sipa_l_per_detaik": 0,
        "kapasitas_intake_air_baku_l_per_detaik": 0,
        "catatan": "Sumber Dana Pembangunan juga berasal dari dana APBD dan PDAM"
    },
    "3302_PURWOKERTO_SELATAN": {
        "key": "3302_PURWOKERTO_SELATAN",
        "nama": "PURWOKERTO SELATAN",
        "kode_daerah": "3302",
        "kode_daerah_simspam": "3302",
        "kapasitas_terpasang_l_per_detik": 112,
        "kapasitas_produksi_l_per_detik": 109,
        "kapasitas_distribusi_l_per_detik": 93,
        "kapasitas_air_terjual_l_per_detik": 53.8,
        "kapasitas_belum_terpakai_l_per_detik": 3,
        "kehilangan_air_persen": 42.28,
        "sambungan_rumah_unit": 8804,
        "updated_at": "2019/10/22",
        "rimayat_sr": {
            "2010": 1524,
            "2011": 1512,
            "2012": 1510,
            "2013": 1553,
            "2014": 1549,
            "2015": 4842,
            "2016": 5600,
            "2017": 7728,
            "2018": 9223
        },
        "kat_pelayanan": "KOTA",
        "kat_pengelolaan": "PDAM",
        "hidran_umum_unit": 0,
        "sambungan_komersial_non_domestik": 419,
        "penduduk_terlayani_jiwa": 34857,
        "persentase_pelayanan_persen": 2.24,
        "total_jam_oprasional_perhari": 22,
        "target_sambungan_rumah_unit": 1000,
        "target_penduduk_terlayani_jiwa": 38816,
        "target_cakupan_layanan_persen": 49,
        "idle_capacity_yang_dimanfaatkan_l_per_detik": 0,
        "rencana_penambahan_capacity_uprating_l_per_detaik": 0,
        "rencana_penambahan_capacity_pembangunan_unit_baru_l_per_detaik": 0,
        "rencana_kebutuhan_capacity_air_baku_l_per_detik": 400,
        "rencana_kebutuhan_capacity_intek_l_per_detik": 0,
        "kapasita_sumber_air_baku_l_per_detik": 238,
        "alokasi_kapasitas_air_baku_sesuai_sipa_l_per_detaik": 400,
        "kapasitas_intake_air_baku_l_per_detaik": 200,
        "catatan": "Sumber Dana Pembangunan juga berasal dari dan APBD dan PDAM;\nData kapasitas unit masih kosong."
    },
    "3302_KEMRANJEN": {
        "key": "3302_KEMRANJEN",
        "nama": "KEMRANJEN",
        "kode_daerah": "3302",
        "kode_daerah_simspam": "3302",
        "kapasitas_terpasang_l_per_detik": 23,
        "kapasitas_produksi_l_per_detik": 23,
        "kapasitas_distribusi_l_per_detik": 42,
        "kapasitas_air_terjual_l_per_detik": 35.4,
        "kapasitas_belum_terpakai_l_per_detik": 1,
        "kehilangan_air_persen": 14.82,
        "sambungan_rumah_unit": 855,
        "updated_at": "2019/10/22",
        "rimayat_sr": {
            "2010": 0,
            "2011": 0,
            "2012": 0,
            "2013": 0,
            "2014": 148,
            "2015": 250,
            "2016": 493,
            "2017": 693,
            "2018": 888
        },
        "kat_pelayanan": "KOTA",
        "kat_pengelolaan": "PDAM",
        "hidran_umum_unit": 0,
        "sambungan_komersial_non_domestik": 33,
        "penduduk_terlayani_jiwa": 3085,
        "persentase_pelayanan_persen": 0,
        "total_jam_oprasional_perhari": 0,
        "target_sambungan_rumah_unit": 500,
        "target_penduduk_terlayani_jiwa": 18484,
        "target_cakupan_layanan_persen": 4,
        "idle_capacity_yang_dimanfaatkan_l_per_detik": 0,
        "rencana_penambahan_capacity_uprating_l_per_detaik": 0,
        "rencana_penambahan_capacity_pembangunan_unit_baru_l_per_detaik": 0,
        "rencana_kebutuhan_capacity_air_baku_l_per_detik": 60,
        "rencana_kebutuhan_capacity_intek_l_per_detik": 0,
        "kapasita_sumber_air_baku_l_per_detik": 30,
        "alokasi_kapasitas_air_baku_sesuai_sipa_l_per_detaik": 60,
        "kapasitas_intake_air_baku_l_per_detaik": 0,
        "catatan": null
    },
    "3302_WANGON": {
        "key": "3302_WANGON",
        "nama": "WANGON",
        "kode_daerah": "3302",
        "kode_daerah_simspam": "3302",
        "kapasitas_terpasang_l_per_detik": 48,
        "kapasitas_produksi_l_per_detik": 47,
        "kapasitas_distribusi_l_per_detik": 40,
        "kapasitas_air_terjual_l_per_detik": 29.93,
        "kapasitas_belum_terpakai_l_per_detik": 1,
        "kehilangan_air_persen": 24.51,
        "sambungan_rumah_unit": 4671,
        "updated_at": "2019/10/22",
        "rimayat_sr": {
            "2010": 0,
            "2011": 0,
            "2012": 0,
            "2013": 4125,
            "2014": 4195,
            "2015": 4215,
            "2016": 4263,
            "2017": 4503,
            "2018": 5564
        },
        "kat_pelayanan": "KOTA",
        "kat_pengelolaan": "PDAM",
        "hidran_umum_unit": 12,
        "sambungan_komersial_non_domestik": 881,
        "penduduk_terlayani_jiwa": 18070,
        "persentase_pelayanan_persen": 0,
        "total_jam_oprasional_perhari": 22,
        "target_sambungan_rumah_unit": 500,
        "target_penduduk_terlayani_jiwa": 19876,
        "target_cakupan_layanan_persen": 26,
        "idle_capacity_yang_dimanfaatkan_l_per_detik": 0,
        "rencana_penambahan_capacity_uprating_l_per_detaik": 0,
        "rencana_penambahan_capacity_pembangunan_unit_baru_l_per_detaik": 0,
        "rencana_kebutuhan_capacity_air_baku_l_per_detik": 0,
        "rencana_kebutuhan_capacity_intek_l_per_detik": 0,
        "kapasita_sumber_air_baku_l_per_detik": 50,
        "alokasi_kapasitas_air_baku_sesuai_sipa_l_per_detaik": 0,
        "kapasitas_intake_air_baku_l_per_detaik": 50,
        "catatan": null
    },
    "3302_AJIBARANG_DAN_PEKUNCEN": {
        "key": "3302_AJIBARANG_DAN_PEKUNCEN",
        "nama": "AJIBARANG DAN PEKUNCEN",
        "kode_daerah": "3302",
        "kode_daerah_simspam": "3302",
        "kapasitas_terpasang_l_per_detik": 88,
        "kapasitas_produksi_l_per_detik": 86,
        "kapasitas_distribusi_l_per_detik": 106,
        "kapasitas_air_terjual_l_per_detik": 71.35,
        "kapasitas_belum_terpakai_l_per_detik": 2,
        "kehilangan_air_persen": 32.64,
        "sambungan_rumah_unit": 7170,
        "updated_at": "2019/10/22",
        "rimayat_sr": {
            "2010": 0,
            "2011": 0,
            "2012": 0,
            "2013": 5559,
            "2014": 6405,
            "2015": 6892,
            "2016": 6952,
            "2017": 7240,
            "2018": 7954
        },
        "kat_pelayanan": "KOTA",
        "kat_pengelolaan": "PDAM",
        "hidran_umum_unit": 4,
        "sambungan_komersial_non_domestik": 780,
        "penduduk_terlayani_jiwa": 27513,
        "persentase_pelayanan_persen": 0,
        "total_jam_oprasional_perhari": 23,
        "target_sambungan_rumah_unit": 500,
        "target_penduduk_terlayani_jiwa": 29403,
        "target_cakupan_layanan_persen": 18,
        "idle_capacity_yang_dimanfaatkan_l_per_detik": 0,
        "rencana_penambahan_capacity_uprating_l_per_detaik": 0,
        "rencana_penambahan_capacity_pembangunan_unit_baru_l_per_detaik": 0,
        "rencana_kebutuhan_capacity_air_baku_l_per_detik": 0,
        "rencana_kebutuhan_capacity_intek_l_per_detik": 0,
        "kapasita_sumber_air_baku_l_per_detik": 148,
        "alokasi_kapasitas_air_baku_sesuai_sipa_l_per_detaik": 0,
        "kapasitas_intake_air_baku_l_per_detaik": 126,
        "catatan": null
    },
    "3302_CILONGOK": {
        "key": "3302_CILONGOK",
        "nama": "CILONGOK",
        "kode_daerah": "3302",
        "kode_daerah_simspam": "3302",
        "kapasitas_terpasang_l_per_detik": 65,
        "kapasitas_produksi_l_per_detik": 63,
        "kapasitas_distribusi_l_per_detik": 104,
        "kapasitas_air_terjual_l_per_detik": 69.86,
        "kapasitas_belum_terpakai_l_per_detik": 2,
        "kehilangan_air_persen": 32.64,
        "sambungan_rumah_unit": 2364,
        "updated_at": "2019/10/22",
        "rimayat_sr": {
            "2010": 0,
            "2011": 0,
            "2012": 0,
            "2013": 1476,
            "2014": 1527,
            "2015": 1575,
            "2016": 1947,
            "2017": 2149,
            "2018": 2567
        },
        "kat_pelayanan": "KOTA",
        "kat_pengelolaan": "SWASTA",
        "hidran_umum_unit": 2,
        "sambungan_komersial_non_domestik": 201,
        "penduduk_terlayani_jiwa": 9102,
        "persentase_pelayanan_persen": 0,
        "total_jam_oprasional_perhari": 24,
        "target_sambungan_rumah_unit": 500,
        "target_penduduk_terlayani_jiwa": 10985,
        "target_cakupan_layanan_persen": 9,
        "idle_capacity_yang_dimanfaatkan_l_per_detik": 0,
        "rencana_penambahan_capacity_uprating_l_per_detaik": 0,
        "rencana_penambahan_capacity_pembangunan_unit_baru_l_per_detaik": 0,
        "rencana_kebutuhan_capacity_air_baku_l_per_detik": 0,
        "rencana_kebutuhan_capacity_intek_l_per_detik": 0,
        "kapasita_sumber_air_baku_l_per_detik": 75,
        "alokasi_kapasitas_air_baku_sesuai_sipa_l_per_detaik": 0,
        "kapasitas_intake_air_baku_l_per_detaik": 75,
        "catatan": null
    },
    "3302_PURWOJATI_DAN_JATILAWANG": {
        "key": "3302_PURWOJATI_DAN_JATILAWANG",
        "nama": "PURWOJATI DAN JATILAWANG",
        "kode_daerah": "3302",
        "kode_daerah_simspam": "3302",
        "kapasitas_terpasang_l_per_detik": 50,
        "kapasitas_produksi_l_per_detik": 49,
        "kapasitas_distribusi_l_per_detik": 40,
        "kapasitas_air_terjual_l_per_detik": 26.64,
        "kapasitas_belum_terpakai_l_per_detik": 1,
        "kehilangan_air_persen": 33.1,
        "sambungan_rumah_unit": 2212,
        "updated_at": "2019/11/04",
        "rimayat_sr": {
            "2010": 0,
            "2011": 0,
            "2012": 0,
            "2013": 2681,
            "2014": 3420,
            "2015": 3783,
            "2016": 3813,
            "2017": 4294,
            "2018": 4675
        },
        "kat_pelayanan": "KOTA",
        "kat_pengelolaan": "PDAM",
        "hidran_umum_unit": 5,
        "sambungan_komersial_non_domestik": 2217,
        "penduduk_terlayani_jiwa": 13272,
        "persentase_pelayanan_persen": 0,
        "total_jam_oprasional_perhari": 23,
        "target_sambungan_rumah_unit": 175,
        "target_penduduk_terlayani_jiwa": 1050,
        "target_cakupan_layanan_persen": 44,
        "idle_capacity_yang_dimanfaatkan_l_per_detik": 0,
        "rencana_penambahan_capacity_uprating_l_per_detaik": 0,
        "rencana_penambahan_capacity_pembangunan_unit_baru_l_per_detaik": 0,
        "rencana_kebutuhan_capacity_air_baku_l_per_detik": 0,
        "rencana_kebutuhan_capacity_intek_l_per_detik": 0,
        "kapasita_sumber_air_baku_l_per_detik": 53,
        "alokasi_kapasitas_air_baku_sesuai_sipa_l_per_detaik": 0,
        "kapasitas_intake_air_baku_l_per_detaik": 50,
        "catatan": null
    }
}