{
    "7102_TONDANO__BARAT": {
        "key": "7102_TONDANO__BARAT",
        "nama": "Tondano  Barat",
        "kode_daerah": "7102",
        "kode_daerah_simspam": "7102",
        "kapasitas_terpasang_l_per_detik": 80,
        "kapasitas_produksi_l_per_detik": 56,
        "kapasitas_distribusi_l_per_detik": 56,
        "kapasitas_air_terjual_l_per_detik": 0,
        "kapasitas_belum_terpakai_l_per_detik": 24,
        "kehilangan_air_persen": 100,
        "sambungan_rumah_unit": 2421,
        "updated_at": "2019/11/26",
        "rimayat_sr": {
            "2010": 0,
            "2011": 0,
            "2012": 0,
            "2013": 0,
            "2014": 0,
            "2015": 0,
            "2016": 0,
            "2017": 0,
            "2018": 2006
        },
        "kat_pelayanan": "KOTA",
        "kat_pengelolaan": "PDAM",
        "hidran_umum_unit": 4,
        "sambungan_komersial_non_domestik": 10,
        "penduduk_terlayani_jiwa": 9219,
        "persentase_pelayanan_persen": 2.97,
        "total_jam_oprasional_perhari": 15,
        "target_sambungan_rumah_unit": 3600,
        "target_penduduk_terlayani_jiwa": 13114,
        "target_cakupan_layanan_persen": 4,
        "idle_capacity_yang_dimanfaatkan_l_per_detik": 0,
        "rencana_penambahan_capacity_uprating_l_per_detaik": 0,
        "rencana_penambahan_capacity_pembangunan_unit_baru_l_per_detaik": 15,
        "rencana_kebutuhan_capacity_air_baku_l_per_detik": 100,
        "rencana_kebutuhan_capacity_intek_l_per_detik": 0,
        "kapasita_sumber_air_baku_l_per_detik": 100,
        "alokasi_kapasitas_air_baku_sesuai_sipa_l_per_detaik": 100,
        "kapasitas_intake_air_baku_l_per_detaik": 100,
        "catatan": null
    },
    "7102_TONDANO__TIMUR": {
        "key": "7102_TONDANO__TIMUR",
        "nama": "Tondano  Timur",
        "kode_daerah": "7102",
        "kode_daerah_simspam": "7102",
        "kapasitas_terpasang_l_per_detik": 80,
        "kapasitas_produksi_l_per_detik": 56,
        "kapasitas_distribusi_l_per_detik": 56,
        "kapasitas_air_terjual_l_per_detik": 0,
        "kapasitas_belum_terpakai_l_per_detik": 24,
        "kehilangan_air_persen": 100,
        "sambungan_rumah_unit": 1197,
        "updated_at": "2019/11/26",
        "rimayat_sr": {
            "2010": 0,
            "2011": 0,
            "2012": 0,
            "2013": 0,
            "2014": 0,
            "2015": 0,
            "2016": 0,
            "2017": 0,
            "2018": 0
        },
        "kat_pelayanan": "KOTA",
        "kat_pengelolaan": "PDAM",
        "hidran_umum_unit": 0,
        "sambungan_komersial_non_domestik": 0,
        "penduduk_terlayani_jiwa": 4361,
        "persentase_pelayanan_persen": 1.41,
        "total_jam_oprasional_perhari": 15,
        "target_sambungan_rumah_unit": 1350,
        "target_penduduk_terlayani_jiwa": 4918,
        "target_cakupan_layanan_persen": 1,
        "idle_capacity_yang_dimanfaatkan_l_per_detik": 0,
        "rencana_penambahan_capacity_uprating_l_per_detaik": 0,
        "rencana_penambahan_capacity_pembangunan_unit_baru_l_per_detaik": 5,
        "rencana_kebutuhan_capacity_air_baku_l_per_detik": 0,
        "rencana_kebutuhan_capacity_intek_l_per_detik": 0,
        "kapasita_sumber_air_baku_l_per_detik": 20,
        "alokasi_kapasitas_air_baku_sesuai_sipa_l_per_detaik": 0,
        "kapasitas_intake_air_baku_l_per_detaik": 30,
        "catatan": null
    },
    "7102_TONDANO__SELATAN": {
        "key": "7102_TONDANO__SELATAN",
        "nama": "Tondano  Selatan",
        "kode_daerah": "7102",
        "kode_daerah_simspam": "7102",
        "kapasitas_terpasang_l_per_detik": 50,
        "kapasitas_produksi_l_per_detik": 35,
        "kapasitas_distribusi_l_per_detik": 35,
        "kapasitas_air_terjual_l_per_detik": 5.82,
        "kapasitas_belum_terpakai_l_per_detik": 15,
        "kehilangan_air_persen": 83.37,
        "sambungan_rumah_unit": 1352,
        "updated_at": "2019/11/26",
        "rimayat_sr": {
            "2010": 0,
            "2011": 0,
            "2012": 0,
            "2013": 0,
            "2014": 0,
            "2015": 0,
            "2016": 0,
            "2017": 0,
            "2018": 0
        },
        "kat_pelayanan": "DESA",
        "kat_pengelolaan": "PDAM",
        "hidran_umum_unit": 0,
        "sambungan_komersial_non_domestik": 0,
        "penduduk_terlayani_jiwa": 4925,
        "persentase_pelayanan_persen": 1.59,
        "total_jam_oprasional_perhari": 16,
        "target_sambungan_rumah_unit": 1530,
        "target_penduduk_terlayani_jiwa": 5574,
        "target_cakupan_layanan_persen": 2,
        "idle_capacity_yang_dimanfaatkan_l_per_detik": 0,
        "rencana_penambahan_capacity_uprating_l_per_detaik": 0,
        "rencana_penambahan_capacity_pembangunan_unit_baru_l_per_detaik": 5,
        "rencana_kebutuhan_capacity_air_baku_l_per_detik": 0,
        "rencana_kebutuhan_capacity_intek_l_per_detik": 0,
        "kapasita_sumber_air_baku_l_per_detik": 50,
        "alokasi_kapasitas_air_baku_sesuai_sipa_l_per_detaik": 0,
        "kapasitas_intake_air_baku_l_per_detaik": 10,
        "catatan": null
    },
    "7102_TONDANO__UTARA": {
        "key": "7102_TONDANO__UTARA",
        "nama": "Tondano  Utara",
        "kode_daerah": "7102",
        "kode_daerah_simspam": "7102",
        "kapasitas_terpasang_l_per_detik": 20,
        "kapasitas_produksi_l_per_detik": 14,
        "kapasitas_distribusi_l_per_detik": 14,
        "kapasitas_air_terjual_l_per_detik": 6.55,
        "kapasitas_belum_terpakai_l_per_detik": 6,
        "kehilangan_air_persen": 53.21,
        "sambungan_rumah_unit": 1006,
        "updated_at": "2019/10/31",
        "rimayat_sr": {
            "2010": 0,
            "2011": 0,
            "2012": 0,
            "2013": 0,
            "2014": 0,
            "2015": 0,
            "2016": 0,
            "2017": 0,
            "2018": 0
        },
        "kat_pelayanan": "DESA",
        "kat_pengelolaan": "PDAM",
        "hidran_umum_unit": 0,
        "sambungan_komersial_non_domestik": 0,
        "penduduk_terlayani_jiwa": 3665,
        "persentase_pelayanan_persen": 1.18,
        "total_jam_oprasional_perhari": 15,
        "target_sambungan_rumah_unit": 1350,
        "target_penduduk_terlayani_jiwa": 4918,
        "target_cakupan_layanan_persen": 1,
        "idle_capacity_yang_dimanfaatkan_l_per_detik": 0,
        "rencana_penambahan_capacity_uprating_l_per_detaik": 0,
        "rencana_penambahan_capacity_pembangunan_unit_baru_l_per_detaik": 5,
        "rencana_kebutuhan_capacity_air_baku_l_per_detik": 0,
        "rencana_kebutuhan_capacity_intek_l_per_detik": 0,
        "kapasita_sumber_air_baku_l_per_detik": 10,
        "alokasi_kapasitas_air_baku_sesuai_sipa_l_per_detaik": 0,
        "kapasitas_intake_air_baku_l_per_detaik": 10,
        "catatan": null
    },
    "7102_SONDER": {
        "key": "7102_SONDER",
        "nama": "Sonder",
        "kode_daerah": "7102",
        "kode_daerah_simspam": "7102",
        "kapasitas_terpasang_l_per_detik": 50,
        "kapasitas_produksi_l_per_detik": 31,
        "kapasitas_distribusi_l_per_detik": 31,
        "kapasitas_air_terjual_l_per_detik": 1.5,
        "kapasitas_belum_terpakai_l_per_detik": 19,
        "kehilangan_air_persen": 95.16,
        "sambungan_rumah_unit": 990,
        "updated_at": "2019/11/26",
        "rimayat_sr": {
            "2010": 0,
            "2011": 0,
            "2012": 0,
            "2013": 0,
            "2014": 0,
            "2015": 0,
            "2016": 0,
            "2017": 0,
            "2018": 0
        },
        "kat_pelayanan": "DESA",
        "kat_pengelolaan": "PDAM",
        "hidran_umum_unit": 0,
        "sambungan_komersial_non_domestik": 0,
        "penduduk_terlayani_jiwa": 0,
        "persentase_pelayanan_persen": 0,
        "total_jam_oprasional_perhari": 14,
        "target_sambungan_rumah_unit": 1170,
        "target_penduduk_terlayani_jiwa": 4262,
        "target_cakupan_layanan_persen": 1,
        "idle_capacity_yang_dimanfaatkan_l_per_detik": 0,
        "rencana_penambahan_capacity_uprating_l_per_detaik": 0,
        "rencana_penambahan_capacity_pembangunan_unit_baru_l_per_detaik": 5,
        "rencana_kebutuhan_capacity_air_baku_l_per_detik": 0,
        "rencana_kebutuhan_capacity_intek_l_per_detik": 0,
        "kapasita_sumber_air_baku_l_per_detik": 20,
        "alokasi_kapasitas_air_baku_sesuai_sipa_l_per_detaik": 0,
        "kapasitas_intake_air_baku_l_per_detaik": 15,
        "catatan": null
    },
    "7102_KAWANGKOAN": {
        "key": "7102_KAWANGKOAN",
        "nama": "Kawangkoan",
        "kode_daerah": "7102",
        "kode_daerah_simspam": "7102",
        "kapasitas_terpasang_l_per_detik": 155,
        "kapasitas_produksi_l_per_detik": 76,
        "kapasitas_distribusi_l_per_detik": 76,
        "kapasitas_air_terjual_l_per_detik": 7.82,
        "kapasitas_belum_terpakai_l_per_detik": 79,
        "kehilangan_air_persen": 89.71,
        "sambungan_rumah_unit": 2167,
        "updated_at": "2019/10/31",
        "rimayat_sr": {
            "2010": 0,
            "2011": 0,
            "2012": 0,
            "2013": 0,
            "2014": 0,
            "2015": 0,
            "2016": 0,
            "2017": 0,
            "2018": 0
        },
        "kat_pelayanan": "DESA",
        "kat_pengelolaan": "PDAM",
        "hidran_umum_unit": 0,
        "sambungan_komersial_non_domestik": 0,
        "penduduk_terlayani_jiwa": 7894,
        "persentase_pelayanan_persen": 2.54,
        "total_jam_oprasional_perhari": 15,
        "target_sambungan_rumah_unit": 2340,
        "target_penduduk_terlayani_jiwa": 8524,
        "target_cakupan_layanan_persen": 3,
        "idle_capacity_yang_dimanfaatkan_l_per_detik": 0,
        "rencana_penambahan_capacity_uprating_l_per_detaik": 0,
        "rencana_penambahan_capacity_pembangunan_unit_baru_l_per_detaik": 5,
        "rencana_kebutuhan_capacity_air_baku_l_per_detik": 0,
        "rencana_kebutuhan_capacity_intek_l_per_detik": 0,
        "kapasita_sumber_air_baku_l_per_detik": 20,
        "alokasi_kapasitas_air_baku_sesuai_sipa_l_per_detaik": 0,
        "kapasitas_intake_air_baku_l_per_detaik": 30,
        "catatan": null
    },
    "7102_TOMBARIRI": {
        "key": "7102_TOMBARIRI",
        "nama": "Tombariri",
        "kode_daerah": "7102",
        "kode_daerah_simspam": "7102",
        "kapasitas_terpasang_l_per_detik": 90,
        "kapasitas_produksi_l_per_detik": 21,
        "kapasitas_distribusi_l_per_detik": 21,
        "kapasitas_air_terjual_l_per_detik": 3.04,
        "kapasitas_belum_terpakai_l_per_detik": 69,
        "kehilangan_air_persen": 85.52,
        "sambungan_rumah_unit": 825,
        "updated_at": "2019/10/31",
        "rimayat_sr": {
            "2010": 0,
            "2011": 0,
            "2012": 0,
            "2013": 0,
            "2014": 0,
            "2015": 0,
            "2016": 0,
            "2017": 0,
            "2018": 0
        },
        "kat_pelayanan": "KOTA",
        "kat_pengelolaan": "PDAM",
        "hidran_umum_unit": 0,
        "sambungan_komersial_non_domestik": 0,
        "penduduk_terlayani_jiwa": 3005,
        "persentase_pelayanan_persen": 0.97,
        "total_jam_oprasional_perhari": 15,
        "target_sambungan_rumah_unit": 900,
        "target_penduduk_terlayani_jiwa": 3279,
        "target_cakupan_layanan_persen": 1,
        "idle_capacity_yang_dimanfaatkan_l_per_detik": 0,
        "rencana_penambahan_capacity_uprating_l_per_detaik": 0,
        "rencana_penambahan_capacity_pembangunan_unit_baru_l_per_detaik": 5,
        "rencana_kebutuhan_capacity_air_baku_l_per_detik": 5,
        "rencana_kebutuhan_capacity_intek_l_per_detik": 0,
        "kapasita_sumber_air_baku_l_per_detik": 20,
        "alokasi_kapasitas_air_baku_sesuai_sipa_l_per_detaik": 5,
        "kapasitas_intake_air_baku_l_per_detaik": 10,
        "catatan": null
    },
    "7102_ERIS": {
        "key": "7102_ERIS",
        "nama": "Eris",
        "kode_daerah": "7102",
        "kode_daerah_simspam": "7102",
        "kapasitas_terpasang_l_per_detik": 10,
        "kapasitas_produksi_l_per_detik": 6,
        "kapasitas_distribusi_l_per_detik": 6,
        "kapasitas_air_terjual_l_per_detik": 1.67,
        "kapasitas_belum_terpakai_l_per_detik": 4,
        "kehilangan_air_persen": 72.17,
        "sambungan_rumah_unit": 390,
        "updated_at": "2019/10/31",
        "rimayat_sr": {
            "2010": 0,
            "2011": 0,
            "2012": 0,
            "2013": 0,
            "2014": 0,
            "2015": 0,
            "2016": 0,
            "2017": 0,
            "2018": 0
        },
        "kat_pelayanan": "KOTA",
        "kat_pengelolaan": "PDAM",
        "hidran_umum_unit": 0,
        "sambungan_komersial_non_domestik": 0,
        "penduduk_terlayani_jiwa": 1421,
        "persentase_pelayanan_persen": 0.46,
        "total_jam_oprasional_perhari": 15,
        "target_sambungan_rumah_unit": 540,
        "target_penduduk_terlayani_jiwa": 1967,
        "target_cakupan_layanan_persen": 1,
        "idle_capacity_yang_dimanfaatkan_l_per_detik": 0,
        "rencana_penambahan_capacity_uprating_l_per_detaik": 0,
        "rencana_penambahan_capacity_pembangunan_unit_baru_l_per_detaik": 5,
        "rencana_kebutuhan_capacity_air_baku_l_per_detik": 0,
        "rencana_kebutuhan_capacity_intek_l_per_detik": 0,
        "kapasita_sumber_air_baku_l_per_detik": 10,
        "alokasi_kapasitas_air_baku_sesuai_sipa_l_per_detaik": 0,
        "kapasitas_intake_air_baku_l_per_detaik": 5,
        "catatan": null
    },
    "7102_KOMBI": {
        "key": "7102_KOMBI",
        "nama": "Kombi",
        "kode_daerah": "7102",
        "kode_daerah_simspam": "7102",
        "kapasitas_terpasang_l_per_detik": 5,
        "kapasitas_produksi_l_per_detik": 3,
        "kapasitas_distribusi_l_per_detik": 3,
        "kapasitas_air_terjual_l_per_detik": 3.12,
        "kapasitas_belum_terpakai_l_per_detik": 3,
        "kehilangan_air_persen": -24.8,
        "sambungan_rumah_unit": 113,
        "updated_at": "2019/10/31",
        "rimayat_sr": {
            "2010": 0,
            "2011": 0,
            "2012": 0,
            "2013": 0,
            "2014": 0,
            "2015": 0,
            "2016": 0,
            "2017": 0,
            "2018": 0
        },
        "kat_pelayanan": "KOTA",
        "kat_pengelolaan": "PDAM",
        "hidran_umum_unit": 0,
        "sambungan_komersial_non_domestik": 0,
        "penduduk_terlayani_jiwa": 412,
        "persentase_pelayanan_persen": 0.13,
        "total_jam_oprasional_perhari": 15,
        "target_sambungan_rumah_unit": 450,
        "target_penduduk_terlayani_jiwa": 1639,
        "target_cakupan_layanan_persen": 1,
        "idle_capacity_yang_dimanfaatkan_l_per_detik": 0,
        "rencana_penambahan_capacity_uprating_l_per_detaik": 0,
        "rencana_penambahan_capacity_pembangunan_unit_baru_l_per_detaik": 5,
        "rencana_kebutuhan_capacity_air_baku_l_per_detik": 0,
        "rencana_kebutuhan_capacity_intek_l_per_detik": 0,
        "kapasita_sumber_air_baku_l_per_detik": 10,
        "alokasi_kapasitas_air_baku_sesuai_sipa_l_per_detaik": 0,
        "kapasitas_intake_air_baku_l_per_detaik": 5,
        "catatan": null
    },
    "7102_REMBOKEN": {
        "key": "7102_REMBOKEN",
        "nama": "Remboken",
        "kode_daerah": "7102",
        "kode_daerah_simspam": "7102",
        "kapasitas_terpasang_l_per_detik": 30,
        "kapasitas_produksi_l_per_detik": 20,
        "kapasitas_distribusi_l_per_detik": 20,
        "kapasitas_air_terjual_l_per_detik": 5.6,
        "kapasitas_belum_terpakai_l_per_detik": 10,
        "kehilangan_air_persen": 72,
        "sambungan_rumah_unit": 718,
        "updated_at": "2019/10/31",
        "rimayat_sr": {
            "2010": 0,
            "2011": 0,
            "2012": 0,
            "2013": 0,
            "2014": 0,
            "2015": 0,
            "2016": 0,
            "2017": 0,
            "2018": 0
        },
        "kat_pelayanan": "KOTA",
        "kat_pengelolaan": "PDAM",
        "hidran_umum_unit": 0,
        "sambungan_komersial_non_domestik": 0,
        "penduduk_terlayani_jiwa": 2616,
        "persentase_pelayanan_persen": 0.84,
        "total_jam_oprasional_perhari": 15,
        "target_sambungan_rumah_unit": 900,
        "target_penduduk_terlayani_jiwa": 3279,
        "target_cakupan_layanan_persen": 1,
        "idle_capacity_yang_dimanfaatkan_l_per_detik": 0,
        "rencana_penambahan_capacity_uprating_l_per_detaik": 0,
        "rencana_penambahan_capacity_pembangunan_unit_baru_l_per_detaik": 5,
        "rencana_kebutuhan_capacity_air_baku_l_per_detik": 0,
        "rencana_kebutuhan_capacity_intek_l_per_detik": 0,
        "kapasita_sumber_air_baku_l_per_detik": 10,
        "alokasi_kapasitas_air_baku_sesuai_sipa_l_per_detaik": 0,
        "kapasitas_intake_air_baku_l_per_detaik": 40,
        "catatan": null
    },
    "7102_LANGOWAN": {
        "key": "7102_LANGOWAN",
        "nama": "Langowan",
        "kode_daerah": "7102",
        "kode_daerah_simspam": "7102",
        "kapasitas_terpasang_l_per_detik": 30,
        "kapasitas_produksi_l_per_detik": 19,
        "kapasitas_distribusi_l_per_detik": 19,
        "kapasitas_air_terjual_l_per_detik": 5.23,
        "kapasitas_belum_terpakai_l_per_detik": 11,
        "kehilangan_air_persen": 72.47,
        "sambungan_rumah_unit": 1120,
        "updated_at": "2019/10/31",
        "rimayat_sr": {
            "2010": 0,
            "2011": 0,
            "2012": 0,
            "2013": 0,
            "2014": 0,
            "2015": 0,
            "2016": 0,
            "2017": 0,
            "2018": 0
        },
        "kat_pelayanan": "KOTA",
        "kat_pengelolaan": "PDAM",
        "hidran_umum_unit": 0,
        "sambungan_komersial_non_domestik": 0,
        "penduduk_terlayani_jiwa": 4080,
        "persentase_pelayanan_persen": 1.31,
        "total_jam_oprasional_perhari": 15,
        "target_sambungan_rumah_unit": 1350,
        "target_penduduk_terlayani_jiwa": 4918,
        "target_cakupan_layanan_persen": 1,
        "idle_capacity_yang_dimanfaatkan_l_per_detik": 0,
        "rencana_penambahan_capacity_uprating_l_per_detaik": 0,
        "rencana_penambahan_capacity_pembangunan_unit_baru_l_per_detaik": 5,
        "rencana_kebutuhan_capacity_air_baku_l_per_detik": 5,
        "rencana_kebutuhan_capacity_intek_l_per_detik": 0,
        "kapasita_sumber_air_baku_l_per_detik": 10,
        "alokasi_kapasitas_air_baku_sesuai_sipa_l_per_detaik": 5,
        "kapasitas_intake_air_baku_l_per_detaik": 10,
        "catatan": null
    },
    "7102_TOMPASO": {
        "key": "7102_TOMPASO",
        "nama": "Tompaso",
        "kode_daerah": "7102",
        "kode_daerah_simspam": "7102",
        "kapasitas_terpasang_l_per_detik": 20,
        "kapasitas_produksi_l_per_detik": 10,
        "kapasitas_distribusi_l_per_detik": 10,
        "kapasitas_air_terjual_l_per_detik": 9.21,
        "kapasitas_belum_terpakai_l_per_detik": 10,
        "kehilangan_air_persen": 7.9,
        "sambungan_rumah_unit": 560,
        "updated_at": "2019/10/31",
        "rimayat_sr": {
            "2010": 0,
            "2011": 0,
            "2012": 0,
            "2013": 0,
            "2014": 0,
            "2015": 0,
            "2016": 0,
            "2017": 0,
            "2018": 0
        },
        "kat_pelayanan": "KOTA",
        "kat_pengelolaan": "PDAM",
        "hidran_umum_unit": 0,
        "sambungan_komersial_non_domestik": 0,
        "penduduk_terlayani_jiwa": 2040,
        "persentase_pelayanan_persen": 0.66,
        "total_jam_oprasional_perhari": 15,
        "target_sambungan_rumah_unit": 900,
        "target_penduduk_terlayani_jiwa": 3279,
        "target_cakupan_layanan_persen": 1,
        "idle_capacity_yang_dimanfaatkan_l_per_detik": 0,
        "rencana_penambahan_capacity_uprating_l_per_detaik": 0,
        "rencana_penambahan_capacity_pembangunan_unit_baru_l_per_detaik": 5,
        "rencana_kebutuhan_capacity_air_baku_l_per_detik": 0,
        "rencana_kebutuhan_capacity_intek_l_per_detik": 0,
        "kapasita_sumber_air_baku_l_per_detik": 10,
        "alokasi_kapasitas_air_baku_sesuai_sipa_l_per_detaik": 0,
        "kapasitas_intake_air_baku_l_per_detaik": 5,
        "catatan": null
    },
    "7102_MAPANGET": {
        "key": "7102_MAPANGET",
        "nama": "Mapanget",
        "kode_daerah": "7102",
        "kode_daerah_simspam": "7102",
        "kapasitas_terpasang_l_per_detik": 70,
        "kapasitas_produksi_l_per_detik": 45,
        "kapasitas_distribusi_l_per_detik": 45,
        "kapasitas_air_terjual_l_per_detik": 4.08,
        "kapasitas_belum_terpakai_l_per_detik": 26,
        "kehilangan_air_persen": 90.83,
        "sambungan_rumah_unit": 1306,
        "updated_at": "2019/10/31",
        "rimayat_sr": {
            "2010": 0,
            "2011": 0,
            "2012": 0,
            "2013": 0,
            "2014": 0,
            "2015": 0,
            "2016": 0,
            "2017": 0,
            "2018": 0
        },
        "kat_pelayanan": "DESA",
        "kat_pengelolaan": "PDAM",
        "hidran_umum_unit": 0,
        "sambungan_komersial_non_domestik": 0,
        "penduduk_terlayani_jiwa": 4758,
        "persentase_pelayanan_persen": 1.53,
        "total_jam_oprasional_perhari": 15,
        "target_sambungan_rumah_unit": 1440,
        "target_penduduk_terlayani_jiwa": 5246,
        "target_cakupan_layanan_persen": 2,
        "idle_capacity_yang_dimanfaatkan_l_per_detik": 0,
        "rencana_penambahan_capacity_uprating_l_per_detaik": 0,
        "rencana_penambahan_capacity_pembangunan_unit_baru_l_per_detaik": 5,
        "rencana_kebutuhan_capacity_air_baku_l_per_detik": 5,
        "rencana_kebutuhan_capacity_intek_l_per_detik": 0,
        "kapasita_sumber_air_baku_l_per_detik": 20,
        "alokasi_kapasitas_air_baku_sesuai_sipa_l_per_detaik": 5,
        "kapasitas_intake_air_baku_l_per_detaik": 10,
        "catatan": null
    },
    "7102_TONDANO_UTARA_II": {
        "key": "7102_TONDANO_UTARA_II",
        "nama": "Tondano Utara II",
        "kode_daerah": "7102",
        "kode_daerah_simspam": "7102",
        "kapasitas_terpasang_l_per_detik": 20,
        "kapasitas_produksi_l_per_detik": 0,
        "kapasitas_distribusi_l_per_detik": 0,
        "kapasitas_air_terjual_l_per_detik": 0,
        "kapasitas_belum_terpakai_l_per_detik": 20,
        "kehilangan_air_persen": 0,
        "sambungan_rumah_unit": 0,
        "updated_at": "2018/11/13",
        "rimayat_sr": {
            "2010": 0,
            "2011": 0,
            "2012": 0,
            "2013": 0,
            "2014": 0,
            "2015": 0,
            "2016": 0,
            "2017": 0,
            "2018": 0
        },
        "kat_pelayanan": "KOTA",
        "kat_pengelolaan": "PDAM",
        "hidran_umum_unit": 0,
        "sambungan_komersial_non_domestik": 0,
        "penduduk_terlayani_jiwa": 0,
        "persentase_pelayanan_persen": 0,
        "total_jam_oprasional_perhari": 0,
        "target_sambungan_rumah_unit": 0,
        "target_penduduk_terlayani_jiwa": 0,
        "target_cakupan_layanan_persen": 0,
        "idle_capacity_yang_dimanfaatkan_l_per_detik": 0,
        "rencana_penambahan_capacity_uprating_l_per_detaik": 0,
        "rencana_penambahan_capacity_pembangunan_unit_baru_l_per_detaik": 0,
        "rencana_kebutuhan_capacity_air_baku_l_per_detik": 0,
        "rencana_kebutuhan_capacity_intek_l_per_detik": 0,
        "kapasita_sumber_air_baku_l_per_detik": 0,
        "alokasi_kapasitas_air_baku_sesuai_sipa_l_per_detaik": 0,
        "kapasitas_intake_air_baku_l_per_detaik": 0,
        "catatan": "Masih dalam proses pembangunan"
    },
    "7102_KAKAS": {
        "key": "7102_KAKAS",
        "nama": "Kakas",
        "kode_daerah": "7102",
        "kode_daerah_simspam": "7102",
        "kapasitas_terpasang_l_per_detik": 20,
        "kapasitas_produksi_l_per_detik": 10,
        "kapasitas_distribusi_l_per_detik": 10,
        "kapasitas_air_terjual_l_per_detik": 9.21,
        "kapasitas_belum_terpakai_l_per_detik": 10,
        "kehilangan_air_persen": 7.9,
        "sambungan_rumah_unit": 500,
        "updated_at": "2019/11/27",
        "rimayat_sr": {
            "2010": 0,
            "2011": 0,
            "2012": 0,
            "2013": 0,
            "2014": 0,
            "2015": 0,
            "2016": 0,
            "2017": 0,
            "2018": 0
        },
        "kat_pelayanan": "DESA",
        "kat_pengelolaan": "PDAM",
        "hidran_umum_unit": 0,
        "sambungan_komersial_non_domestik": 0,
        "penduduk_terlayani_jiwa": 0,
        "persentase_pelayanan_persen": 0,
        "total_jam_oprasional_perhari": 8,
        "target_sambungan_rumah_unit": 0,
        "target_penduduk_terlayani_jiwa": 0,
        "target_cakupan_layanan_persen": 0,
        "idle_capacity_yang_dimanfaatkan_l_per_detik": 0,
        "rencana_penambahan_capacity_uprating_l_per_detaik": 0,
        "rencana_penambahan_capacity_pembangunan_unit_baru_l_per_detaik": 0,
        "rencana_kebutuhan_capacity_air_baku_l_per_detik": 200,
        "rencana_kebutuhan_capacity_intek_l_per_detik": 0,
        "kapasita_sumber_air_baku_l_per_detik": 200,
        "alokasi_kapasitas_air_baku_sesuai_sipa_l_per_detaik": 200,
        "kapasitas_intake_air_baku_l_per_detaik": 0,
        "catatan": null
    },
    "7102_KALI": {
        "key": "7102_KALI",
        "nama": "Kali",
        "kode_daerah": "7102",
        "kode_daerah_simspam": "7102",
        "kapasitas_terpasang_l_per_detik": 20,
        "kapasitas_produksi_l_per_detik": 10,
        "kapasitas_distribusi_l_per_detik": 10,
        "kapasitas_air_terjual_l_per_detik": 2.21,
        "kapasitas_belum_terpakai_l_per_detik": 10,
        "kehilangan_air_persen": 77.9,
        "sambungan_rumah_unit": 200,
        "updated_at": "2019/11/27",
        "rimayat_sr": {
            "2010": 0,
            "2011": 0,
            "2012": 0,
            "2013": 0,
            "2014": 0,
            "2015": 0,
            "2016": 0,
            "2017": 0,
            "2018": 0
        },
        "kat_pelayanan": "DESA",
        "kat_pengelolaan": "PDAM",
        "hidran_umum_unit": 0,
        "sambungan_komersial_non_domestik": 0,
        "penduduk_terlayani_jiwa": 0,
        "persentase_pelayanan_persen": 0,
        "total_jam_oprasional_perhari": 18,
        "target_sambungan_rumah_unit": 0,
        "target_penduduk_terlayani_jiwa": 0,
        "target_cakupan_layanan_persen": 0,
        "idle_capacity_yang_dimanfaatkan_l_per_detik": 0,
        "rencana_penambahan_capacity_uprating_l_per_detaik": 0,
        "rencana_penambahan_capacity_pembangunan_unit_baru_l_per_detaik": 0,
        "rencana_kebutuhan_capacity_air_baku_l_per_detik": 0,
        "rencana_kebutuhan_capacity_intek_l_per_detik": 0,
        "kapasita_sumber_air_baku_l_per_detik": 0,
        "alokasi_kapasitas_air_baku_sesuai_sipa_l_per_detaik": 0,
        "kapasitas_intake_air_baku_l_per_detaik": 20,
        "catatan": null
    }
}